pymoog/__init__.py
pymoog/abfind.py
pymoog/binary.py
pymoog/blends.py
pymoog/cog.py
pymoog/contri_func.py
pymoog/deprecated.py
pymoog/internal.py
pymoog/line_data.py
pymoog/model.py
pymoog/mpfit.py
pymoog/private.py
pymoog/rundir_num.py
pymoog/synth.py
pymoog/weedout.py
pymoog/files/atoms.csv
pymoog/files/dissociation_energy_list.csv
pymoog/files/grid_points_kurucz.csv
pymoog/files/moog_nosm/README.md
pymoog/files/moog_nosm/manual/MOOG Manual.aux
pymoog/files/moog_nosm/manual/MOOG Manual.log
pymoog/files/moog_nosm/manual/MOOG Manual.pdf
pymoog/files/moog_nosm/manual/MOOG Manual.synctex.gz
pymoog/files/moog_nosm/manual/MOOG Manual.tex
pymoog/files/moog_nosm/moog_nosm_FEB2017/Abfind.f
pymoog/files/moog_nosm/moog_nosm_FEB2017/Abpop.f
pymoog/files/moog_nosm/moog_nosm_FEB2017/Abunplot.f
pymoog/files/moog_nosm/moog_nosm_FEB2017/Atmos.com
pymoog/files/moog_nosm/moog_nosm_FEB2017/Barklem.dat
pymoog/files/moog_nosm/moog_nosm_FEB2017/BarklemUV.dat
pymoog/files/moog_nosm/moog_nosm_FEB2017/Batom.f
pymoog/files/moog_nosm/moog_nosm_FEB2017/Begin.f
pymoog/files/moog_nosm/moog_nosm_FEB2017/Binary.f
pymoog/files/moog_nosm/moog_nosm_FEB2017/Binplot.f
pymoog/files/moog_nosm/moog_nosm_FEB2017/Binplotprep.f
pymoog/files/moog_nosm/moog_nosm_FEB2017/Blankstring.f
pymoog/files/moog_nosm/moog_nosm_FEB2017/Blends.f
pymoog/files/moog_nosm/moog_nosm_FEB2017/Bmolec.f
pymoog/files/moog_nosm/moog_nosm_FEB2017/Boxit.f
pymoog/files/moog_nosm/moog_nosm_FEB2017/Calmod.f
pymoog/files/moog_nosm/moog_nosm_FEB2017/Cdcalc.f
pymoog/files/moog_nosm/moog_nosm_FEB2017/Chabund.f
pymoog/files/moog_nosm/moog_nosm_FEB2017/Cog.f
pymoog/files/moog_nosm/moog_nosm_FEB2017/Cogplot.f
pymoog/files/moog_nosm/moog_nosm_FEB2017/Cogsyn.f
pymoog/files/moog_nosm/moog_nosm_FEB2017/Correl.f
pymoog/files/moog_nosm/moog_nosm_FEB2017/Crosscorr.f
pymoog/files/moog_nosm/moog_nosm_FEB2017/Curve.f
pymoog/files/moog_nosm/moog_nosm_FEB2017/Dampdat.com
pymoog/files/moog_nosm/moog_nosm_FEB2017/Damping.f
pymoog/files/moog_nosm/moog_nosm_NOV2019/rulerwd.egg-info/PKG-INFO
pymoog/files/moog_nosm/moog_nosm_NOV2019/rulerwd.egg-info/SOURCES.txt
pymoog/files/moog_nosm/moog_nosm_NOV2019/rulerwd.egg-info/dependency_links.txt
pymoog/files/moog_nosm/moog_nosm_NOV2019/rulerwd.egg-info/not-zip-safe
pymoog/files/moog_nosm/moog_nosm_NOV2019/rulerwd.egg-info/top_level.txt
pymoog-0.1.2.dist-info/LICENCE
pymoog-0.1.2.dist-info/METADATA
pymoog-0.1.2.dist-info/WHEEL
pymoog-0.1.2.dist-info/top_level.txt
pymoog-0.1.2.dist-info/RECORD
