Metadata-Version: 2.1
Name: pymoog
Version: 0.1.2
Summary: The python wrapper to run LTE spectra synthesis code MOOG.
Home-page: https://github.com/MingjieJian/pymoog
Author: Mingjie Jian
Author-email: ssaajianmingjie@gmail.com
Classifier: Programming Language :: Python :: 3
Classifier: License :: OSI Approved :: MIT License
Classifier: Framework :: IPython
Classifier: Operating System :: OS Independent
Classifier: Development Status :: 2 - Pre-Alpha
Classifier: Topic :: Scientific/Engineering :: Astronomy
Requires-Python: >=3.5
License-File: LICENCE
Requires-Dist: numpy (>=1.18.0)
Requires-Dist: pandas (>=1.0.0)
Requires-Dist: matplotlib (>=3.1.0)
Requires-Dist: mendeleev (>=0.6.0)
Requires-Dist: scipy (>=1.4.0)
Requires-Dist: astropy (>=4.0)
Requires-Dist: spectres
Requires-Dist: tqdm
Requires-Dist: zenodo-get
